multiplexer_llm/__init__.py
multiplexer_llm/exceptions.py
multiplexer_llm/multiplexer.py
multiplexer_llm/test_helper.py
multiplexer_llm/types.py
multiplexer_llm-0.1.6.data/data/requirements.txt
multiplexer_llm-0.1.6.dist-info/METADATA
multiplexer_llm-0.1.6.dist-info/WHEEL
multiplexer_llm-0.1.6.dist-info/top_level.txt
multiplexer_llm-0.1.6.dist-info/RECORD
